[
	{
		"inputs": [
			{
				"internalType": "address",
				"name": "_owner",
				"type": "address"
			}
		],
		"stateMutability": "nonpayable",
		"type": "constructor"
	},
	{
		"inputs": [
			{
				"internalType": "uint256",
				"name": "_id",
				"type": "uint256"
			},
			{
				"internalType": "string",
				"name": "_ts",
				"type": "string"
			}
		],
		"name": "acceptBatch",
		"outputs": [],
		"stateMutability": "nonpayable",
		"type": "function"
	},
	{
		"inputs": [
			{
				"internalType": "address",
				"name": "_add",
				"type": "address"
			}
		],
		"name": "addAdmin",
		"outputs": [],
		"stateMutability": "nonpayable",
		"type": "function"
	},
	{
		"inputs": [
			{
				"internalType": "address",
				"name": "_root",
				"type": "address"
			},
			{
				"internalType": "string",
				"name": "_name",
				"type": "string"
			},
			{
				"internalType": "string",
				"name": "_ts",
				"type": "string"
			},
			{
				"internalType": "string",
				"name": "_secret",
				"type": "string"
			}
		],
		"name": "addBatch",
		"outputs": [],
		"stateMutability": "nonpayable",
		"type": "function"
	},
	{
		"inputs": [
			{
				"internalType": "string",
				"name": "_name",
				"type": "string"
			},
			{
				"internalType": "uint256",
				"name": "_level",
				"type": "uint256"
			},
			{
				"internalType": "string",
				"name": "_lat",
				"type": "string"
			},
			{
				"internalType": "string",
				"name": "_lon",
				"type": "string"
			},
			{
				"internalType": "address",
				"name": "_id",
				"type": "address"
			}
		],
		"name": "addNode",
		"outputs": [],
		"stateMutability": "nonpayable",
		"type": "function"
	},
	{
		"inputs": [
			{
				"internalType": "address",
				"name": "",
				"type": "address"
			}
		],
		"name": "adminMapping",
		"outputs": [
			{
				"internalType": "bool",
				"name": "",
				"type": "bool"
			}
		],
		"stateMutability": "view",
		"type": "function"
	},
	{
		"inputs": [],
		"name": "batchCount",
		"outputs": [
			{
				"internalType": "uint256",
				"name": "",
				"type": "uint256"
			}
		],
		"stateMutability": "view",
		"type": "function"
	},
	{
		"inputs": [
			{
				"internalType": "uint256",
				"name": "",
				"type": "uint256"
			}
		],
		"name": "batchIds",
		"outputs": [
			{
				"internalType": "uint256",
				"name": "",
				"type": "uint256"
			}
		],
		"stateMutability": "view",
		"type": "function"
	},
	{
		"inputs": [
			{
				"internalType": "uint256",
				"name": "",
				"type": "uint256"
			}
		],
		"name": "batchMapping",
		"outputs": [
			{
				"internalType": "uint256",
				"name": "id",
				"type": "uint256"
			},
			{
				"internalType": "string",
				"name": "name",
				"type": "string"
			},
			{
				"internalType": "string",
				"name": "secret",
				"type": "string"
			},
			{
				"internalType": "uint256",
				"name": "status",
				"type": "uint256"
			},
			{
				"internalType": "bool",
				"name": "exists",
				"type": "bool"
			}
		],
		"stateMutability": "view",
		"type": "function"
	},
	{
		"inputs": [
			{
				"internalType": "address",
				"name": "_add",
				"type": "address"
			}
		],
		"name": "nodeBatches",
		"outputs": [
			{
				"internalType": "uint256[]",
				"name": "",
				"type": "uint256[]"
			}
		],
		"stateMutability": "view",
		"type": "function"
	},
	{
		"inputs": [],
		"name": "nodeCount",
		"outputs": [
			{
				"internalType": "uint256",
				"name": "",
				"type": "uint256"
			}
		],
		"stateMutability": "view",
		"type": "function"
	},
	{
		"inputs": [
			{
				"internalType": "uint256",
				"name": "",
				"type": "uint256"
			}
		],
		"name": "nodeIds",
		"outputs": [
			{
				"internalType": "address",
				"name": "",
				"type": "address"
			}
		],
		"stateMutability": "view",
		"type": "function"
	},
	{
		"inputs": [
			{
				"internalType": "address",
				"name": "",
				"type": "address"
			}
		],
		"name": "nodeMapping",
		"outputs": [
			{
				"internalType": "uint256",
				"name": "noBatches",
				"type": "uint256"
			},
			{
				"internalType": "bool",
				"name": "exists",
				"type": "bool"
			},
			{
				"internalType": "string",
				"name": "name",
				"type": "string"
			},
			{
				"internalType": "uint256",
				"name": "level",
				"type": "uint256"
			},
			{
				"internalType": "address",
				"name": "id",
				"type": "address"
			},
			{
				"internalType": "string",
				"name": "lat",
				"type": "string"
			},
			{
				"internalType": "string",
				"name": "lon",
				"type": "string"
			}
		],
		"stateMutability": "view",
		"type": "function"
	},
	{
		"inputs": [],
		"name": "stopCount",
		"outputs": [
			{
				"internalType": "uint256",
				"name": "",
				"type": "uint256"
			}
		],
		"stateMutability": "view",
		"type": "function"
	},
	{
		"inputs": [
			{
				"internalType": "uint256",
				"name": "",
				"type": "uint256"
			}
		],
		"name": "stopMapping",
		"outputs": [
			{
				"internalType": "address",
				"name": "nodeAddress",
				"type": "address"
			},
			{
				"internalType": "string",
				"name": "timestamp",
				"type": "string"
			}
		],
		"stateMutability": "view",
		"type": "function"
	},
	{
		"inputs": [],
		"name": "superuser",
		"outputs": [
			{
				"internalType": "address",
				"name": "",
				"type": "address"
			}
		],
		"stateMutability": "view",
		"type": "function"
	},
	{
		"inputs": [
			{
				"internalType": "uint256",
				"name": "_id",
				"type": "uint256"
			}
		],
		"name": "viewStops",
		"outputs": [
			{
				"internalType": "uint256[]",
				"name": "",
				"type": "uint256[]"
			}
		],
		"stateMutability": "view",
		"type": "function"
	}
]